co_automation/__init__.py
co_automation/conflict_check.py
co_automation/create_schedule_co.py
co_automation/create_sn_co.py
co_automation/date_logic.py
co_automation/get_sn_co_item.py
co_automation/get_sn_token.py
co_automation/risk_assessment.py
co_automation/test_lib.py
co_automation/update_status.py
co_automation-0.1.21.dist-info/METADATA
co_automation-0.1.21.dist-info/WHEEL
co_automation-0.1.21.dist-info/top_level.txt
co_automation-0.1.21.dist-info/RECORD
