Metadata-Version: 2.4
Name: co_automation
Version: 0.1.21
Summary: A Python package to create servicenow change order
Home-page: 
Author: 
Author-email: 
License: BSD 2-clause
Requires-Dist: mpi4py>=2.0
Requires-Dist: numpy
Dynamic: license
Dynamic: requires-dist
Dynamic: summary
